admin_cursor_paginator/__init__.py
admin_cursor_paginator/admin.py
admin_cursor_paginator/cursor.py
admin_cursor_paginator/paginator.py
admin_cursor_paginator/version.py
admin_cursor_paginator/views.py
admin_cursor_paginator/templates/admin_cursor_paginator/change_list.html
admin_cursor_paginator/templates/admin_cursor_paginator/pagination.html
admin_cursor_paginator/templatetags/__init__.py
admin_cursor_paginator/templatetags/admin_cursor_paginator_tags.py
django_admin_cursor_paginator-0.1.2.dist-info/LICENSE
django_admin_cursor_paginator-0.1.2.dist-info/METADATA
django_admin_cursor_paginator-0.1.2.dist-info/WHEEL
django_admin_cursor_paginator-0.1.2.dist-info/top_level.txt
django_admin_cursor_paginator-0.1.2.dist-info/RECORD
